language_balls/__init__.py
language_balls/logos.jpeg
language_balls-0.815.5.dist-info/METADATA
language_balls-0.815.5.dist-info/WHEEL
language_balls-0.815.5.dist-info/entry_points.txt
language_balls-0.815.5.dist-info/top_level.txt
language_balls-0.815.5.dist-info/RECORD
