Metadata-Version: 2.4
Name: language-balls
Version: 0.815.5
Summary: Animated language balls moving at different periods
Author: Emrah Diril
Author-email: emrah@diril.org
Classifier: Programming Language :: Python :: 3
Classifier: License :: OSI Approved :: MIT License
Classifier: Operating System :: OS Independent
Requires-Python: >=3.9
Requires-Dist: dearpygui==1.11.1
Dynamic: author
Dynamic: author-email
Dynamic: classifier
Dynamic: requires-dist
Dynamic: requires-python
Dynamic: summary
